{
  "designerVersion" : "1.10.50",
  "id" : "dataPersonalForm",
  "name" : "dataPersonalForm",
  "lastUpdate" : 1588690055601,
  "rows" : [
    [
      {
        "type" : "container",
        "dimension" : {
          "xs" : 12
        },
        "propertyValues" : { },
        "reference" : "d5584b7a-d1b4-4432-bcdd-e7df9fce3306",
        "hasValidationError" : false,
        "id" : "pbContainer",
        "rows" : [
          [
            {
              "type" : "component",
              "dimension" : {
                "xs" : 12
              },
              "propertyValues" : {
                "labelHidden" : {
                  "type" : "constant",
                  "value" : false
                },
                "hidden" : {
                  "type" : "constant",
                  "value" : false
                },
                "level" : {
                  "type" : "constant",
                  "value" : "Level 1"
                },
                "cssClasses" : {
                  "type" : "constant",
                  "value" : ""
                },
                "widgetId" : {
                  "type" : "constant",
                  "value" : "pbTitle"
                },
                "readOnly" : {
                  "type" : "constant",
                  "value" : false
                },
                "label" : {
                  "type" : "interpolation"
                },
                "text" : {
                  "type" : "interpolation",
                  "value" : "Datos Personales Admisión"
                },
                "alignment" : {
                  "type" : "constant",
                  "value" : "center"
                },
                "class" : {
                  "type" : "constant",
                  "value" : "org.bonitasoft.web.designer.experimental.parametrizedWidget.TitleWidget"
                },
                "dimension" : {
                  "type" : "constant",
                  "value" : 12
                }
              },
              "reference" : "e0ad7a57-d662-43fc-beb2-e717a151b5dd",
              "hasValidationError" : false,
              "id" : "pbTitle"
            }
          ],
          [
            {
              "type" : "component",
              "dimension" : {
                "xs" : 12
              },
              "propertyValues" : {
                "allowHtml" : {
                  "type" : "constant",
                  "value" : true
                },
                "labelHidden" : {
                  "type" : "constant",
                  "value" : true
                },
                "hidden" : {
                  "type" : "constant",
                  "value" : false
                },
                "cssClasses" : {
                  "type" : "constant",
                  "value" : ""
                },
                "widgetId" : {
                  "type" : "constant",
                  "value" : "pbText"
                },
                "readOnly" : {
                  "type" : "constant",
                  "value" : false
                },
                "label" : {
                  "type" : "interpolation"
                },
                "text" : {
                  "type" : "interpolation",
                  "value" : "{{ task.displayDescription }}"
                },
                "alignment" : {
                  "type" : "constant",
                  "value" : "left"
                },
                "class" : {
                  "type" : "constant",
                  "value" : "org.bonitasoft.web.designer.experimental.parametrizedWidget.TextWidget"
                },
                "dimension" : {
                  "type" : "constant",
                  "value" : 12
                }
              },
              "reference" : "6b65c186-c602-404d-8fc3-30173cfd2839",
              "hasValidationError" : false,
              "id" : "pbText"
            }
          ]
        ]
      }
    ],
    [
      {
        "type" : "formContainer",
        "dimension" : {
          "xs" : 12
        },
        "propertyValues" : { },
        "reference" : "7146f242-b825-4614-9aaa-943cb1a099f3",
        "hasValidationError" : false,
        "id" : "pbFormContainer",
        "container" : {
          "type" : "container",
          "dimension" : {
            "xs" : 12
          },
          "propertyValues" : { },
          "reference" : "12c286e1-3b28-44ff-aef2-3cd60f8d3f74",
          "hasValidationError" : false,
          "id" : "pbContainer",
          "rows" : [
            [
              {
                "type" : "component",
                "dimension" : {
                  "xs" : 12
                },
                "propertyValues" : {
                  "labelHidden" : {
                    "type" : "constant",
                    "value" : false
                  },
                  "hidden" : {
                    "type" : "constant",
                    "value" : false
                  },
                  "level" : {
                    "type" : "constant",
                    "value" : "Level 4"
                  },
                  "cssClasses" : {
                    "type" : "constant",
                    "value" : ""
                  },
                  "widgetId" : {
                    "type" : "constant",
                    "value" : "pbTitle"
                  },
                  "readOnly" : {
                    "type" : "constant",
                    "value" : false
                  },
                  "label" : {
                    "type" : "interpolation"
                  },
                  "text" : {
                    "type" : "interpolation",
                    "value" : "Solicitante"
                  },
                  "alignment" : {
                    "type" : "constant",
                    "value" : "left"
                  },
                  "class" : {
                    "type" : "constant",
                    "value" : "org.bonitasoft.web.designer.experimental.parametrizedWidget.TitleWidget"
                  },
                  "dimension" : {
                    "type" : "constant",
                    "value" : 12
                  }
                },
                "reference" : "e01d58fa-516d-4fb0-a789-57f1ee297ff1",
                "hasValidationError" : false,
                "id" : "pbTitle"
              }
            ],
            [
              {
                "type" : "container",
                "dimension" : {
                  "xs" : 12
                },
                "propertyValues" : {
                  "repeatedCollection" : {
                    "type" : "variable",
                    "value" : ""
                  },
                  "labelHidden" : {
                    "type" : "constant",
                    "value" : false
                  },
                  "hidden" : {
                    "type" : "constant",
                    "value" : false
                  },
                  "cssClasses" : {
                    "type" : "constant",
                    "value" : ""
                  },
                  "widgetId" : {
                    "type" : "constant"
                  },
                  "readOnly" : {
                    "type" : "constant",
                    "value" : false
                  },
                  "label" : {
                    "type" : "interpolation"
                  },
                  "alignment" : {
                    "type" : "constant",
                    "value" : "left"
                  },
                  "class" : {
                    "type" : "constant",
                    "value" : "org.bonitasoft.web.designer.experimental.parametrizedWidget.WidgetContainer"
                  },
                  "dimension" : {
                    "type" : "constant",
                    "value" : 12
                  }
                },
                "reference" : "88bf2430-a6c1-48ff-841f-acd5cdbe083f",
                "hasValidationError" : false,
                "id" : "pbContainer",
                "rows" : [
                  [
                    {
                      "type" : "component",
                      "dimension" : {
                        "xs" : 10
                      },
                      "propertyValues" : {
                        "hidden" : {
                          "type" : "constant",
                          "value" : false
                        },
                        "cssClasses" : {
                          "type" : "constant",
                          "value" : ""
                        },
                        "widgetId" : {
                          "type" : "constant",
                          "value" : "pbInput"
                        },
                        "labelWidth" : {
                          "type" : "constant",
                          "value" : 4
                        },
                        "readOnly" : {
                          "type" : "constant",
                          "value" : false
                        },
                        "label" : {
                          "type" : "interpolation",
                          "value" : "Nombre"
                        },
                        "type" : {
                          "type" : "constant",
                          "value" : "text"
                        },
                        "required" : {
                          "type" : "constant",
                          "value" : true
                        },
                        "labelHidden" : {
                          "type" : "constant",
                          "value" : false
                        },
                        "labelPosition" : {
                          "type" : "constant",
                          "value" : "left"
                        },
                        "placeholder" : {
                          "type" : "constant"
                        },
                        "alignment" : {
                          "type" : "constant",
                          "value" : "left"
                        },
                        "class" : {
                          "type" : "constant",
                          "value" : "org.bonitasoft.web.designer.experimental.parametrizedWidget.InputWidget"
                        },
                        "dimension" : {
                          "type" : "constant",
                          "value" : 12
                        },
                        "value" : {
                          "type" : "variable",
                          "value" : "person.name"
                        },
                        "minLength" : {
                          "type" : "constant",
                          "value" : ""
                        },
                        "maxLength" : {
                          "type" : "constant",
                          "value" : ""
                        },
                        "min" : {
                          "type" : "constant"
                        },
                        "max" : {
                          "type" : "constant"
                        },
                        "step" : {
                          "type" : "constant",
                          "value" : 1
                        }
                      },
                      "reference" : "7489e534-1d92-4922-8f19-1518ce84ed02",
                      "hasValidationError" : false,
                      "id" : "pbInput"
                    }
                  ],
                  [
                    {
                      "type" : "component",
                      "dimension" : {
                        "xs" : 10
                      },
                      "propertyValues" : {
                        "hidden" : {
                          "type" : "constant",
                          "value" : false
                        },
                        "cssClasses" : {
                          "type" : "constant",
                          "value" : ""
                        },
                        "widgetId" : {
                          "type" : "constant",
                          "value" : "pbInput"
                        },
                        "labelWidth" : {
                          "type" : "constant",
                          "value" : 4
                        },
                        "readOnly" : {
                          "type" : "constant",
                          "value" : false
                        },
                        "label" : {
                          "type" : "interpolation",
                          "value" : "Apellido"
                        },
                        "type" : {
                          "type" : "constant",
                          "value" : "text"
                        },
                        "required" : {
                          "type" : "constant",
                          "value" : true
                        },
                        "labelHidden" : {
                          "type" : "constant",
                          "value" : false
                        },
                        "labelPosition" : {
                          "type" : "constant",
                          "value" : "left"
                        },
                        "placeholder" : {
                          "type" : "constant"
                        },
                        "alignment" : {
                          "type" : "constant",
                          "value" : "left"
                        },
                        "class" : {
                          "type" : "constant",
                          "value" : "org.bonitasoft.web.designer.experimental.parametrizedWidget.InputWidget"
                        },
                        "dimension" : {
                          "type" : "constant",
                          "value" : 12
                        },
                        "value" : {
                          "type" : "variable",
                          "value" : "person.surname"
                        },
                        "minLength" : {
                          "type" : "constant",
                          "value" : ""
                        },
                        "maxLength" : {
                          "type" : "constant",
                          "value" : ""
                        },
                        "min" : {
                          "type" : "constant"
                        },
                        "max" : {
                          "type" : "constant"
                        },
                        "step" : {
                          "type" : "constant",
                          "value" : 1
                        }
                      },
                      "reference" : "b6532ae2-cb33-4556-b9b6-c0438e7ea45e",
                      "hasValidationError" : false,
                      "id" : "pbInput"
                    }
                  ],
                  [
                    {
                      "type" : "component",
                      "dimension" : {
                        "xs" : 10
                      },
                      "propertyValues" : {
                        "hidden" : {
                          "type" : "constant",
                          "value" : false
                        },
                        "dateFormat" : {
                          "type" : "constant",
                          "value" : "MM/dd/yyyy"
                        },
                        "cssClasses" : {
                          "type" : "constant",
                          "value" : ""
                        },
                        "widgetId" : {
                          "type" : "constant",
                          "value" : "pbDatePicker"
                        },
                        "labelWidth" : {
                          "type" : "constant",
                          "value" : 4
                        },
                        "readOnly" : {
                          "type" : "constant",
                          "value" : false
                        },
                        "label" : {
                          "type" : "interpolation",
                          "value" : "Fecha Nacimiento"
                        },
                        "type" : {
                          "type" : "constant"
                        },
                        "required" : {
                          "type" : "constant",
                          "value" : true
                        },
                        "todayLabel" : {
                          "type" : "constant",
                          "value" : "Hoy"
                        },
                        "labelHidden" : {
                          "type" : "constant",
                          "value" : false
                        },
                        "showToday" : {
                          "type" : "constant",
                          "value" : true
                        },
                        "labelPosition" : {
                          "type" : "constant",
                          "value" : "left"
                        },
                        "placeholder" : {
                          "type" : "constant",
                          "value" : "Enter a date (mm/dd/yyyy)"
                        },
                        "alignment" : {
                          "type" : "constant",
                          "value" : "left"
                        },
                        "class" : {
                          "type" : "constant",
                          "value" : "org.bonitasoft.web.designer.experimental.parametrizedWidget.DatePickerWidget"
                        },
                        "dimension" : {
                          "type" : "constant",
                          "value" : 12
                        },
                        "value" : {
                          "type" : "variable",
                          "value" : "person.birthdate"
                        }
                      },
                      "reference" : "272517d3-7d6c-4500-8e69-c51f0c469a4e",
                      "hasValidationError" : false,
                      "id" : "pbDatePicker"
                    }
                  ],
                  [
                    {
                      "type" : "component",
                      "dimension" : {
                        "xs" : 10
                      },
                      "propertyValues" : {
                        "hidden" : {
                          "type" : "constant",
                          "value" : false
                        },
                        "cssClasses" : {
                          "type" : "constant",
                          "value" : ""
                        },
                        "widgetId" : {
                          "type" : "constant",
                          "value" : "pbInput"
                        },
                        "labelWidth" : {
                          "type" : "constant",
                          "value" : 4
                        },
                        "readOnly" : {
                          "type" : "constant",
                          "value" : false
                        },
                        "label" : {
                          "type" : "interpolation",
                          "value" : "Sexo"
                        },
                        "type" : {
                          "type" : "constant",
                          "value" : "text"
                        },
                        "required" : {
                          "type" : "constant",
                          "value" : true
                        },
                        "labelHidden" : {
                          "type" : "constant",
                          "value" : false
                        },
                        "labelPosition" : {
                          "type" : "constant",
                          "value" : "left"
                        },
                        "placeholder" : {
                          "type" : "constant"
                        },
                        "alignment" : {
                          "type" : "constant",
                          "value" : "left"
                        },
                        "class" : {
                          "type" : "constant",
                          "value" : "org.bonitasoft.web.designer.experimental.parametrizedWidget.InputWidget"
                        },
                        "dimension" : {
                          "type" : "constant",
                          "value" : 12
                        },
                        "value" : {
                          "type" : "variable",
                          "value" : "person.sex"
                        },
                        "minLength" : {
                          "type" : "constant",
                          "value" : ""
                        },
                        "maxLength" : {
                          "type" : "constant",
                          "value" : ""
                        },
                        "min" : {
                          "type" : "constant"
                        },
                        "max" : {
                          "type" : "constant"
                        },
                        "step" : {
                          "type" : "constant",
                          "value" : 1
                        }
                      },
                      "reference" : "6d378fc4-0c33-4ec8-aaa3-d3bfb319a9ec",
                      "hasValidationError" : false,
                      "id" : "pbInput"
                    }
                  ],
                  [
                    {
                      "type" : "component",
                      "dimension" : {
                        "xs" : 3
                      },
                      "propertyValues" : {
                        "cssClasses" : {
                          "type" : "constant",
                          "value" : ""
                        },
                        "hidden" : {
                          "type" : "constant",
                          "value" : false
                        },
                        "labelHidden" : {
                          "type" : "constant",
                          "value" : true
                        },
                        "label" : {
                          "type" : "interpolation",
                          "value" : "Default label"
                        },
                        "labelPosition" : {
                          "type" : "constant",
                          "value" : "top"
                        },
                        "labelWidth" : {
                          "type" : "constant",
                          "value" : 4
                        },
                        "allowHTML" : {
                          "type" : "constant",
                          "value" : true
                        },
                        "text" : {
                          "type" : "interpolation",
                          "value" : ""
                        },
                        "alignment" : {
                          "type" : "constant",
                          "value" : "left"
                        }
                      },
                      "reference" : "8dd56ef5-cb00-4fd2-9395-c9469c1868f2",
                      "hasValidationError" : false,
                      "id" : "pbText"
                    },
                    {
                      "type" : "component",
                      "dimension" : {
                        "xs" : 6
                      },
                      "propertyValues" : {
                        "labelHidden" : {
                          "type" : "constant",
                          "value" : false
                        },
                        "hidden" : {
                          "type" : "constant",
                          "value" : false
                        },
                        "cssClasses" : {
                          "type" : "constant",
                          "value" : ""
                        },
                        "widgetId" : {
                          "type" : "constant",
                          "value" : "pbCheckbox"
                        },
                        "disabled" : {
                          "type" : "constant",
                          "value" : false
                        },
                        "label" : {
                          "type" : "interpolation",
                          "value" : "¿Estudias?"
                        },
                        "alignment" : {
                          "type" : "constant",
                          "value" : "left"
                        },
                        "class" : {
                          "type" : "constant",
                          "value" : "org.bonitasoft.web.designer.experimental.parametrizedWidget.CheckboxWidget"
                        },
                        "dimension" : {
                          "type" : "constant",
                          "value" : 12
                        },
                        "value" : {
                          "type" : "variable",
                          "value" : "person.isStudent"
                        },
                        "required" : {
                          "type" : "constant",
                          "value" : false
                        }
                      },
                      "reference" : "d6a67cc7-1a3c-4027-a0d2-6f09212e3e8a",
                      "hasValidationError" : false,
                      "id" : "pbCheckbox"
                    }
                  ]
                ]
              }
            ],
            [
              {
                "type" : "component",
                "dimension" : {
                  "xs" : 12
                },
                "propertyValues" : {
                  "removeItem" : {
                    "type" : "variable"
                  },
                  "hidden" : {
                    "type" : "constant",
                    "value" : false
                  },
                  "cssClasses" : {
                    "type" : "constant",
                    "value" : ""
                  },
                  "widgetId" : {
                    "type" : "constant",
                    "value" : "pbButton"
                  },
                  "buttonStyle" : {
                    "type" : "constant",
                    "value" : "primary"
                  },
                  "readOnly" : {
                    "type" : "constant",
                    "value" : false
                  },
                  "label" : {
                    "type" : "interpolation",
                    "value" : "Enviar"
                  },
                  "dataToSend" : {
                    "type" : "expression",
                    "value" : "formOutput"
                  },
                  "dataFromError" : {
                    "type" : "variable",
                    "value" : "formOutput._submitError"
                  },
                  "labelHidden" : {
                    "type" : "constant",
                    "value" : false
                  },
                  "collectionPosition" : {
                    "type" : "constant"
                  },
                  "targetUrlOnSuccess" : {
                    "type" : "interpolation",
                    "value" : "/bonita"
                  },
                  "action" : {
                    "type" : "constant",
                    "value" : "Submit task"
                  },
                  "collectionToModify" : {
                    "type" : "variable"
                  },
                  "valueToAdd" : {
                    "type" : "expression"
                  },
                  "disabled" : {
                    "type" : "expression",
                    "value" : "$form.$invalid"
                  },
                  "alignment" : {
                    "type" : "constant",
                    "value" : "center"
                  },
                  "class" : {
                    "type" : "constant",
                    "value" : "org.bonitasoft.web.designer.experimental.parametrizedWidget.ButtonWidget"
                  },
                  "dimension" : {
                    "type" : "constant",
                    "value" : 12
                  },
                  "assign" : {
                    "type" : "constant",
                    "value" : false
                  },
                  "url" : {
                    "type" : "interpolation"
                  },
                  "responseStatusCode" : {
                    "type" : "variable",
                    "value" : ""
                  },
                  "dataFromSuccess" : {
                    "type" : "variable",
                    "value" : ""
                  },
                  "closeOnSuccess" : {
                    "type" : "constant",
                    "value" : false
                  },
                  "modalId" : {
                    "type" : "constant",
                    "value" : ""
                  }
                },
                "reference" : "80729791-34a0-4d95-9e3f-5427a0062932",
                "hasValidationError" : false,
                "id" : "pbButton"
              }
            ],
            [
              {
                "type" : "component",
                "dimension" : {
                  "xs" : 12
                },
                "propertyValues" : {
                  "allowHTML" : {
                    "type" : "constant",
                    "value" : true
                  },
                  "allowHtml" : {
                    "type" : "constant",
                    "value" : true
                  },
                  "labelHidden" : {
                    "type" : "constant",
                    "value" : true
                  },
                  "hidden" : {
                    "type" : "expression",
                    "value" : "!formOutput._submitError.message"
                  },
                  "cssClasses" : {
                    "type" : "constant",
                    "value" : "alert alert-danger col-lg-6 col-lg-offset-3"
                  },
                  "widgetId" : {
                    "type" : "constant",
                    "value" : "pbText"
                  },
                  "readOnly" : {
                    "type" : "constant",
                    "value" : false
                  },
                  "label" : {
                    "type" : "interpolation"
                  },
                  "text" : {
                    "type" : "interpolation",
                    "value" : "<strong>Debug message</strong>\n<br/>\n{{formOutput._submitError.message}}\n{{submit_errors_list}}"
                  },
                  "alignment" : {
                    "type" : "constant",
                    "value" : "left"
                  },
                  "class" : {
                    "type" : "constant",
                    "value" : "org.bonitasoft.web.designer.experimental.parametrizedWidget.TextWidget"
                  },
                  "dimension" : {
                    "type" : "constant",
                    "value" : 12
                  }
                },
                "reference" : "a9543083-37b5-42d6-bfd8-d00f3659566c",
                "hasValidationError" : false,
                "id" : "pbText"
              }
            ]
          ]
        }
      }
    ]
  ],
  "assets" : [
    {
      "id" : "2d313159-15f1-44d7-92a9-46a5d7e1a654",
      "name" : "style.css",
      "type" : "css",
      "order" : 0,
      "external" : false
    }
  ],
  "inactiveAssets" : [ ],
  "variables" : {
    "task" : {
      "type" : "url",
      "value" : [
        "../API/bpm/userTask/{{taskId}}"
      ],
      "exposed" : false
    },
    "submit_errors_list" : {
      "type" : "expression",
      "value" : [
        "if($data.formOutput && $data.formOutput._submitError && $data.formOutput._submitError.explanations){",
        "\tconst liElements = $data.formOutput._submitError.explanations",
        "\t\t.filter(cause => cause !== null)",
        "\t\t.map(cause => \"<li>\" + cause + \"</li>\")",
        "\t\t.join('');",
        "\tif(liElements){",
        "\t\treturn \"<ul>\" + liElements + \"</ul>\";",
        "\t}",
        "}"
      ],
      "exposed" : false
    },
    "person" : {
      "type" : "url",
      "value" : [
        "../{{context.person_ref.link}}"
      ],
      "exposed" : false
    },
    "formOutput" : {
      "type" : "expression",
      "value" : [
        "if( $data.person ){",
        "\treturn {",
        "\t\t//map person variable to expected task contract input",
        "\t\tpersonInput: {",
        "\t\t\tname: $data.person.name !== undefined ? $data.person.name : null,",
        "\t\t\tsurname: $data.person.surname !== undefined ? $data.person.surname : null,",
        "\t\t\tbirthdate: $data.person.birthdate !== undefined ? $data.person.birthdate : null,",
        "\t\t\tsex: $data.person.sex !== undefined ? $data.person.sex : null,",
        "\t\t\tisStudent: $data.person.isStudent !== undefined ? $data.person.isStudent : null,",
        "\t\t\tage: $data.person.age !== undefined ? $data.person.age : null",
        "\t\t}",
        "\t}",
        "}"
      ],
      "exposed" : false
    },
    "context" : {
      "type" : "url",
      "value" : [
        "../API/bpm/userTask/{{taskId}}/context"
      ],
      "exposed" : false
    },
    "taskId" : {
      "type" : "urlparameter",
      "value" : [
        "id"
      ],
      "exposed" : false
    }
  },
  "hasValidationError" : false,
  "uuid" : "1b0b1e23-a8e0-4f52-bd43-99cf9cd2a77e",
  "type" : "form",
  "description" : "Page generated with Bonita UI designer"
}